dinari/__init__.py
dinari/_base_client.py
dinari/_client.py
dinari/_compat.py
dinari/_constants.py
dinari/_exceptions.py
dinari/_files.py
dinari/_models.py
dinari/_qs.py
dinari/_resource.py
dinari/_response.py
dinari/_streaming.py
dinari/_types.py
dinari/_version.py
dinari/py.typed
dinari/_utils/__init__.py
dinari/_utils/_logs.py
dinari/_utils/_proxy.py
dinari/_utils/_reflection.py
dinari/_utils/_streams.py
dinari/_utils/_sync.py
dinari/_utils/_transform.py
dinari/_utils/_typing.py
dinari/_utils/_utils.py
dinari/lib/.keep
dinari/resources/__init__.py
dinari/resources/api/__init__.py
dinari/resources/api/api.py
dinari/resources/api/v2/__init__.py
dinari/resources/api/v2/v2.py
dinari/resources/api/v2/accounts/__init__.py
dinari/resources/api/v2/accounts/accounts.py
dinari/resources/api/v2/accounts/order_fulfillments.py
dinari/resources/api/v2/accounts/order_requests.py
dinari/resources/api/v2/accounts/orders.py
dinari/resources/api/v2/accounts/wallet/__init__.py
dinari/resources/api/v2/accounts/wallet/external.py
dinari/resources/api/v2/accounts/wallet/wallet.py
dinari/resources/api/v2/entities/__init__.py
dinari/resources/api/v2/entities/accounts.py
dinari/resources/api/v2/entities/entities.py
dinari/resources/api/v2/entities/kyc.py
dinari/resources/api/v2/market_data/__init__.py
dinari/resources/api/v2/market_data/market_data.py
dinari/resources/api/v2/market_data/stocks/__init__.py
dinari/resources/api/v2/market_data/stocks/splits.py
dinari/resources/api/v2/market_data/stocks/stocks.py
dinari/types/__init__.py
dinari/types/api/__init__.py
dinari/types/api/v2_get_health_response.py
dinari/types/api/v2/__init__.py
dinari/types/api/v2/account_retrieve_cash_response.py
dinari/types/api/v2/account_retrieve_dividend_payments_response.py
dinari/types/api/v2/account_retrieve_interest_payments_response.py
dinari/types/api/v2/account_retrieve_portfolio_response.py
dinari/types/api/v2/entity.py
dinari/types/api/v2/entity_create_params.py
dinari-0.0.1a1.dist-info/METADATA
dinari-0.0.1a1.dist-info/WHEEL
dinari-0.0.1a1.dist-info/licenses/LICENSE
dinari-0.0.1a1.dist-info/RECORD
